COPYING.LESSER
MANIFEST.in
README.md
setup.py
bin/btrfs-balance-least-used
bin/btrfs-orphan-cleaner-progress
bin/btrfs-search-metadata
bin/btrfs-space-calculator
bin/btrfs-usage-report
btrfs/__init__.py
btrfs/crc32c.py
btrfs/ctree.py
btrfs/free_space_tree.py
btrfs/fs_usage.py
btrfs/ioctl.py
btrfs/utils.py
btrfs/version.py
btrfs/volumes.py
btrfs.egg-info/PKG-INFO
btrfs.egg-info/SOURCES.txt
btrfs.egg-info/dependency_links.txt
btrfs.egg-info/top_level.txt