Metadata-Version: 2.1
Name: btrfs
Version: 15
Summary: Python module to interact programmatically with an online btrfs file system
Home-page: https://github.com/knorrie/python-btrfs
Download-URL: https://github.com/knorrie/python-btrfs/tarball/v15
Author: Hans van Kranenburg
Author-email: hans@knorrie.org
Keywords: btrfs,filesystem
Classifier: Development Status :: 5 - Production/Stable
Classifier: Intended Audience :: Developers
Classifier: Intended Audience :: System Administrators
Classifier: License :: OSI Approved :: GNU Lesser General Public License v3 (LGPLv3)
Classifier: Programming Language :: Python :: 3 :: Only
Classifier: Programming Language :: Python :: Implementation :: CPython
Classifier: Operating System :: POSIX :: Linux
Classifier: Topic :: System :: Filesystems
Classifier: Topic :: System :: Systems Administration
License-File: COPYING.LESSER
